{
  "version": 1,
  "generatorSeed": 20261703,
  "difficulty": "hard",
  "minFrequency": 0,
  "grids": [
    {
      "id": "offline-20261703-0",
      "size": 9,
      "difficulty": "hard",
      "clueCells": [
        [
          0,
          0
        ],
        [
          0,
          4
        ],
        [
          0,
          8
        ],
        [
          1,
          1
        ],
        [
          1,
          5
        ],
        [
          2,
          1
        ],
        [
          2,
          7
        ],
        [
          3,
          2
        ],
        [
          3,
          8
        ],
        [
          4,
          0
        ],
        [
          4,
          3
        ],
        [
          4,
          4
        ],
        [
          5,
          6
        ],
        [
          7,
          5
        ],
        [
          8,
          2
        ]
      ],
      "words": [
        {
          "answer": "OL",
          "clue": "Olympique lyonnais",
          "direction": "down",
          "clueCell": [
            0,
            8
          ],
          "cells": [
            [
              1,
              8
            ],
            [
              2,
              8
            ]
          ]
        },
        {
          "answer": "ADO",
          "clue": "Jeune",
          "direction": "across",
          "clueCell": [
            1,
            5
          ],
          "cells": [
            [
              1,
              6
            ],
            [
              1,
              7
            ],
            [
              1,
              8
            ]
          ]
        },
        {
          "answer": "YO",
          "clue": "Salut",
          "direction": "across",
          "clueCell": [
            4,
            0
          ],
          "cells": [
            [
              4,
              1
            ],
            [
              4,
              2
            ]
          ]
        },
        {
          "answer": "CYBORG",
          "clue": "Mécananthrope",
          "direction": "down",
          "clueCell": [
            2,
            1
          ],
          "cells": [
            [
              3,
              1
            ],
            [
              4,
              1
            ],
            [
              5,
              1
            ],
            [
              6,
              1
            ],
            [
              7,
              1
            ],
            [
              8,
              1
            ]
          ]
        },
        {
          "answer": "ORME",
          "clue": "Ormeau",
          "direction": "down",
          "clueCell": [
            3,
            2
          ],
          "cells": [
            [
              4,
              2
            ],
            [
              5,
              2
            ],
            [
              6,
              2
            ],
            [
              7,
              2
            ]
          ]
        },
        {
          "answer": "CH",
          "clue": "Méthane",
          "direction": "across",
          "clueCell": [
            5,
            6
          ],
          "cells": [
            [
              5,
              7
            ],
            [
              5,
              8
            ]
          ]
        },
        {
          "answer": "CHOPE",
          "clue": "Fait",
          "direction": "down",
          "clueCell": [
            3,
            8
          ],
          "cells": [
            [
              4,
              8
            ],
            [
              5,
              8
            ],
            [
              6,
              8
            ],
            [
              7,
              8
            ],
            [
              8,
              8
            ]
          ]
        },
        {
          "answer": "PEP",
          "clue": "Entrain",
          "direction": "across",
          "clueCell": [
            7,
            5
          ],
          "cells": [
            [
              7,
              6
            ],
            [
              7,
              7
            ],
            [
              7,
              8
            ]
          ]
        },
        {
          "answer": "APP",
          "clue": "Appendicectomie",
          "direction": "down",
          "clueCell": [
            5,
            6
          ],
          "cells": [
            [
              6,
              6
            ],
            [
              7,
              6
            ],
            [
              8,
              6
            ]
          ]
        },
        {
          "answer": "ADEPTE",
          "clue": "Membre",
          "direction": "across",
          "clueCell": [
            8,
            2
          ],
          "cells": [
            [
              8,
              3
            ],
            [
              8,
              4
            ],
            [
              8,
              5
            ],
            [
              8,
              6
            ],
            [
              8,
              7
            ],
            [
              8,
              8
            ]
          ]
        },
        {
          "answer": "CACHET",
          "clue": "Chiffre",
          "direction": "down",
          "clueCell": [
            2,
            7
          ],
          "cells": [
            [
              3,
              7
            ],
            [
              4,
              7
            ],
            [
              5,
              7
            ],
            [
              6,
              7
            ],
            [
              7,
              7
            ],
            [
              8,
              7
            ]
          ]
        },
        {
          "answer": "CLERC",
          "clue": "Lettré",
          "direction": "across",
          "clueCell": [
            3,
            2
          ],
          "cells": [
            [
              3,
              3
            ],
            [
              3,
              4
            ],
            [
              3,
              5
            ],
            [
              3,
              6
            ],
            [
              3,
              7
            ]
          ]
        },
        {
          "answer": "DRAC",
          "clue": "Dragon",
          "direction": "across",
          "clueCell": [
            4,
            4
          ],
          "cells": [
            [
              4,
              5
            ],
            [
              4,
              6
            ],
            [
              4,
              7
            ],
            [
              4,
              8
            ]
          ]
        },
        {
          "answer": "CEDRE",
          "clue": "Abiétacée",
          "direction": "down",
          "clueCell": [
            1,
            5
          ],
          "cells": [
            [
              2,
              5
            ],
            [
              3,
              5
            ],
            [
              4,
              5
            ],
            [
              5,
              5
            ],
            [
              6,
              5
            ]
          ]
        },
        {
          "answer": "CAL",
          "clue": "Durillon",
          "direction": "down",
          "clueCell": [
            0,
            4
          ],
          "cells": [
            [
              1,
              4
            ],
            [
              2,
              4
            ],
            [
              3,
              4
            ]
          ]
        },
        {
          "answer": "BLACK",
          "clue": "Noir",
          "direction": "across",
          "clueCell": [
            2,
            1
          ],
          "cells": [
            [
              2,
              2
            ],
            [
              2,
              3
            ],
            [
              2,
              4
            ],
            [
              2,
              5
            ],
            [
              2,
              6
            ]
          ]
        },
        {
          "answer": "BIC",
          "clue": "Feu",
          "direction": "across",
          "clueCell": [
            1,
            1
          ],
          "cells": [
            [
              1,
              2
            ],
            [
              1,
              3
            ],
            [
              1,
              4
            ]
          ]
        },
        {
          "answer": "RAID",
          "clue": "Voyage",
          "direction": "down",
          "clueCell": [
            4,
            4
          ],
          "cells": [
            [
              5,
              4
            ],
            [
              6,
              4
            ],
            [
              7,
              4
            ],
            [
              8,
              4
            ]
          ]
        },
        {
          "answer": "CATA",
          "clue": "Désastre",
          "direction": "down",
          "clueCell": [
            4,
            3
          ],
          "cells": [
            [
              5,
              3
            ],
            [
              6,
              3
            ],
            [
              7,
              3
            ],
            [
              8,
              3
            ]
          ]
        },
        {
          "answer": "CDR",
          "clue": "Cdk",
          "direction": "across",
          "clueCell": [
            0,
            0
          ],
          "cells": [
            [
              0,
              1
            ],
            [
              0,
              2
            ],
            [
              0,
              3
            ]
          ]
        },
        {
          "answer": "AMA",
          "clue": "Imo",
          "direction": "down",
          "clueCell": [
            0,
            0
          ],
          "cells": [
            [
              1,
              0
            ],
            [
              2,
              0
            ],
            [
              3,
              0
            ]
          ]
        },
        {
          "answer": "HEM",
          "clue": "Hé",
          "direction": "across",
          "clueCell": [
            0,
            4
          ],
          "cells": [
            [
              0,
              5
            ],
            [
              0,
              6
            ],
            [
              0,
              7
            ]
          ]
        },
        {
          "answer": "OEUF",
          "clue": "Cellule-oeuf",
          "direction": "down",
          "clueCell": [
            4,
            0
          ],
          "cells": [
            [
              5,
              0
            ],
            [
              6,
              0
            ],
            [
              7,
              0
            ],
            [
              8,
              0
            ]
          ],
          "image": {
            "asset": "/assets/clues/twemoji/oeuf.svg",
            "alt": "Illustration pour oeuf",
            "source": "Twemoji",
            "license": "CC BY 4.0"
          }
        }
      ]
    }
  ]
}